{"cameraMode":{"drawMode":0,"name":"Shaded","section":"Shading Mode"},"sceneLighting":false,"audioPlay":false,"sceneViewState":{"m_AlwaysRefresh":false,"showFog":true,"showSkybox":false,"showFlares":true,"showImageEffects":true,"showParticleSystems":true,"showVisualEffectGraphs":true,"m_FxEnabled":true},"in2DMode":false,"pivot":{"x":4.250607490539551,"y":2.909562826156616,"z":5.527900695800781},"rotation":{"x":0.1547347456216812,"y":-0.8298542499542236,"z":0.27834242582321169,"w":0.45888519287109377},"size":3.2375259399414064,"orthographic":false}