{"cameraMode":{"drawMode":0,"name":"Shaded","section":"Shading Mode"},"sceneLighting":true,"audioPlay":false,"sceneViewState":{"m_AlwaysRefresh":false,"showFog":true,"showSkybox":true,"showFlares":true,"showImageEffects":true,"showParticleSystems":true,"showVisualEffectGraphs":true,"m_FxEnabled":true},"in2DMode":false,"pivot":{"x":-4.341056823730469,"y":62.901878356933597,"z":-27.782787322998048},"rotation":{"x":0.2727159559726715,"y":0.07083036750555039,"z":-0.008711257949471474,"w":0.9607537984848023},"size":0.17284172773361207,"orthographic":false}